robustness_benchmark/NOT.py
robustness_benchmark/__init__.py
robustness_benchmark/interface.py
robustness_benchmark/score_methods.py
robustness_benchmark-0.0.2.dist-info/METADATA
robustness_benchmark-0.0.2.dist-info/WHEEL
robustness_benchmark-0.0.2.dist-info/top_level.txt
robustness_benchmark-0.0.2.dist-info/RECORD
