Metadata-Version: 2.1
Name: robustness-benchmark
Version: 0.0.2
Summary: Demo module for IQA/VQA Metrics Robustness Benchmark.
Home-page: https://github.com/msu-video-group/MSU_Metrics_Robustness_Benchmark
Author: Anonymous Authors
Project-URL: Bug Tracker, https://github.com/msu-video-group/MSU_Metrics_Robustness_Benchmark/issues
Classifier: Programming Language :: Python :: 3
Classifier: License :: OSI Approved :: MIT License
Classifier: Operating System :: OS Independent
Requires-Python: >=3.7
Requires-Dist: setuptools ==59.5.0
Requires-Dist: av ==10.0.0
Requires-Dist: numpy ==1.19.5
Requires-Dist: pandas ==1.1.5
Requires-Dist: Pillow ==10.0.0
Requires-Dist: scikit-image ==0.17.2
Requires-Dist: scikit-learn ==1.3.0
Requires-Dist: scipy ==1.4.1
Requires-Dist: torchvision ==0.11.3
Requires-Dist: tqdm ==4.57.0
Requires-Dist: torch >=1.10.2
Requires-Dist: opencv-python ==4.2.0.32
